FPGA/projekt/modulo.v
module get_modulo_pq (
    input  wire         clk,
    input  wire         rst,
    input  wire         start,
    input  wire [255:0] a,
    output reg  [63:0]  result,
    output reg          done
);

    // Blum-Blum-Shub parameters
    localparam [31:0] p = 32'd2147483647;
    localparam [31:0] q = 32'd2147483629;
    localparam [63:0] n = p * q;

    always @(posedge clk or posedge rst) begin
        if (rst) begin
            result <= 64'd0;
            done   <= 1'b0;
        end else begin
            done <= 1'b0;

            if (start) begin
                result <= a % n;  // modulo reduction
                done   <= 1'b1;
            end
        end
    end

endmodule

`timescale 1ns/1ps

module tb_get_modulo_pq;

    reg         clk;
    reg         rst;
    reg         start;
    reg [255:0] a;
    wire [63:0] result;
    wire        done;

    // DUT
    get_modulo_pq dut (
        .clk(clk),
        .rst(rst),
        .start(start),
        .a(a),
        .result(result),
        .done(done)
    );

    // Clock: 100 MHz
    initial clk = 0;
    always #5 clk = ~clk;

    // Reference parameters (same as DUT)
    localparam [31:0] p = 32'd2147483647;
    localparam [31:0] q = 32'd2147483629;
    localparam [63:0] n = p * q;

    // Reference calculation
    reg [255:0] ref_a;
    reg [63:0]  ref_mod;

    task run_test(input [255:0] value);
        begin
            ref_a   = value;
            ref_mod = value % n;

            @(posedge clk);
            a     <= value;
            start <= 1'b1;

            @(posedge clk);
            start <= 1'b0;

            wait(done);

            if (result !== ref_mod) begin
                $display("❌ FAIL: a = %h", ref_a);
                $display("   Expected = %h", ref_mod);
                $display("   Got      = %h", result);
            end else begin
                $display("✅ PASS: a = %h, mod n = %h", ref_a, result);
            end

            @(posedge clk);
        end
    endtask

    initial begin
        $dumpfile("get_modulo_pq.vcd");
        $dumpvars(0, tb_get_modulo_pq);

        // Reset
        rst   = 1;
        start = 0;
        a     = 0;

        repeat (2) @(posedge clk);
        rst = 0;

        // ----------------------------
        // Test cases
        // ----------------------------

        // Small value
        run_test(256'd3);

        // Medium value
        run_test(256'd12345);

        // Exactly n
        run_test(n);

        // n + 1
        run_test(n + 1);

        // Large random-looking value
        run_test(256'h123456789ABCDEF0123456789ABCDEF0123456789ABCDEF0);

        // All ones
        run_test({256{1'b1}});

        $display("All tests completed.");
        #50;
        $finish;
    end

endmodule

FPGA/projekt/get_modulo_pq.vcd
$date
	Sun Jan 11 18:43:04 2026
$end
$version
	Icarus Verilog
$end
$timescale
	1ps
$end
$scope module tb_get_modulo_pq $end
$var wire 64 ! result [63:0] $end
$var wire 1 " done $end
$var parameter 64 # n $end
$var parameter 32 $ p $end
$var parameter 32 % q $end
$var reg 256 & a [255:0] $end
$var reg 1 ' clk $end
$var reg 256 ( ref_a [255:0] $end
$var reg 64 ) ref_mod [63:0] $end
$var reg 1 * rst $end
$var reg 1 + start $end
$scope module dut $end
$var wire 256 , a [255:0] $end
$var wire 1 ' clk $end
$var wire 1 * rst $end
$var wire 1 + start $end
$var parameter 64 - n $end
$var parameter 32 . p $end
$var parameter 32 / q $end
$var reg 1 " done $end
$var reg 64 0 result [63:0] $end
$upscope $end
$scope task run_test $end
$var reg 256 1 value [255:0] $end
$upscope $end
$upscope $end
$enddefinitions $end
$comment Show the parameter values. $end
$dumpall
b1111111111111111111111111101101 /
b1111111111111111111111111111111 .
b11111111111111111111111111011000000000000000000000000000010011 -
b1111111111111111111111111101101 %
b1111111111111111111111111111111 $
b11111111111111111111111111011000000000000000000000000000010011 #
$end
#0
$dumpvars
bx 1
b0 0
b0 ,
0+
1*
bx )
bx (
0'
b0 &
0"
b0 !
$end
#5000
1'
#10000
0'
#15000
b11 )
b11 (
b11 1
0*
1'
#20000
0'
#25000
1+
b11 &
b11 ,
1'
#30000
0'
#35000
1"
b11 !
b11 0
0+
1'
#40000
0'
#45000
0"
b11000000111001 )
b11000000111001 (
b11000000111001 1
1'
#50000
0'
#55000
1+
b11000000111001 &
b11000000111001 ,
1'
#60000
0'
#65000
1"
b11000000111001 !
b11000000111001 0
0+
1'
#70000
0'
#75000
0"
b0 )
b11111111111111111111111111011000000000000000000000000000010011 (
b11111111111111111111111111011000000000000000000000000000010011 1
1'
#80000
0'
#85000
1+
b11111111111111111111111111011000000000000000000000000000010011 &
b11111111111111111111111111011000000000000000000000000000010011 ,
1'
#90000
0'
#95000
1"
b0 !
b0 0
0+
1'
#100000
0'
#105000
0"
b1 )
b11111111111111111111111111011000000000000000000000000000010100 (
b11111111111111111111111111011000000000000000000000000000010100 1
1'
#110000
0'
#115000
1+
b11111111111111111111111111011000000000000000000000000000010100 &
b11111111111111111111111111011000000000000000000000000000010100 ,
1'
#120000
0'
#125000
1"
b1 !
b1 0
0+
1'
#130000
0'
#135000
0"
b10010011111101001001101100110111100100000110100010101111100011 )
b100100011010001010110011110001001101010111100110111101111000000010010001101000101011001111000100110101011110011011110111100000001001000110100010101100111100010011010101111001101111011110000 (
b100100011010001010110011110001001101010111100110111101111000000010010001101000101011001111000100110101011110011011110111100000001001000110100010101100111100010011010101111001101111011110000 1
1'
#140000
0'
#145000
1+
b100100011010001010110011110001001101010111100110111101111000000010010001101000101011001111000100110101011110011011110111100000001001000110100010101100111100010011010101111001101111011110000 &
b100100011010001010110011110001001101010111100110111101111000000010010001101000101011001111000100110101011110011011110111100000001001000110100010101100111100010011010101111001101111011110000 ,
1'
#150000
0'
#155000
1"
b10010011111101001001101100110111100100000110100010101111100011 !
b10010011111101001001101100110111100100000110100010101111100011 0
0+
1'
#160000
0'
#165000
0"
b1111010010010100011000010011111000010110110101110100010101111 )
b1111111111111111111111111111111111111111111111111111111111111111111111111111111111111111111111111111111111111111111111111111111111111111111111111111111111111111111111111111111111111111111111111111111111111111111111111111111111111111111111111111111111111111 (
b1111111111111111111111111111111111111111111111111111111111111111111111111111111111111111111111111111111111111111111111111111111111111111111111111111111111111111111111111111111111111111111111111111111111111111111111111111111111111111111111111111111111111111 1
1'
#170000
0'
#175000
1+
b1111111111111111111111111111111111111111111111111111111111111111111111111111111111111111111111111111111111111111111111111111111111111111111111111111111111111111111111111111111111111111111111111111111111111111111111111111111111111111111111111111111111111111 &
b1111111111111111111111111111111111111111111111111111111111111111111111111111111111111111111111111111111111111111111111111111111111111111111111111111111111111111111111111111111111111111111111111111111111111111111111111111111111111111111111111111111111111111 ,
1'
#180000
0'
#185000
1"
b1111010010010100011000010011111000010110110101110100010101111 !
b1111010010010100011000010011111000010110110101110100010101111 0
0+
1'
#190000
0'
#195000
0"
1'
